darklogger/__init__.py
darklogger/darklogger.py
darklogger-1.1.0.dist-info/licenses/LICENSE
darklogger-1.1.0.dist-info/METADATA
darklogger-1.1.0.dist-info/WHEEL
darklogger-1.1.0.dist-info/top_level.txt
darklogger-1.1.0.dist-info/RECORD
